F_Discord_webhook/__init__.py
F_Discord_webhook/webhook.py
tests/__init__.py
tests/test_webhook.py
svc_ds_webhook-2.0.34.dist-info/LICENSE
svc_ds_webhook-2.0.34.dist-info/METADATA
svc_ds_webhook-2.0.34.dist-info/WHEEL
svc_ds_webhook-2.0.34.dist-info/entry_points.txt
svc_ds_webhook-2.0.34.dist-info/top_level.txt
svc_ds_webhook-2.0.34.dist-info/RECORD
