Metadata-Version: 2.1
Name: svc_ds_webhook
Version: 2.0.34
Summary: Discord Webhook Messanger
Home-page: https://github.com/filispeen/so-vits-svc-discord-webhook-notification
Author: FILISPEEN
License: MIT
Keywords: discord,webhook,discord_webhook,svc,so-vits-svc-fork,so-vits-svc-fork-discord-webhook
Classifier: Development Status :: 5 - Production/Stable
Classifier: Intended Audience :: Developers
Classifier: Topic :: Software Development :: Build Tools
Classifier: License :: OSI Approved :: MIT License
Classifier: Programming Language :: Python :: 3.9
Classifier: Programming Language :: Python :: 3.10
License-File: LICENSE
Requires-Dist: discord
Requires-Dist: pytz
Requires-Dist: aiohttp
Requires-Dist: argparse
Requires-Dist: watchdog
